custom_utilities/__init__.py
custom_utilities/custom_utilities.py
custom_utilities/google_cloud_storage.py
custom_utilities/number.py
custom_utilities/output.py
custom_utilities/test.py
custom_utilities/time.py
custom_utilities-0.1.10.dist-info/LICENSE
custom_utilities-0.1.10.dist-info/METADATA
custom_utilities-0.1.10.dist-info/WHEEL
custom_utilities-0.1.10.dist-info/entry_points.txt
custom_utilities-0.1.10.dist-info/top_level.txt
custom_utilities-0.1.10.dist-info/RECORD
