Metadata-Version: 2.1
Name: custom_utilities
Version: 0.1.10
Summary: Python package consisting of custom utilities
Classifier: Programming Language :: Python :: 3
Classifier: License :: OSI Approved :: MIT License
Classifier: Operating System :: OS Independent
Requires-Python: >=3.6
License-File: LICENSE
Requires-Dist: google-cloud-storage
Requires-Dist: tqdm
